{
  "magazine_id": 275,
  "magazine_name": "ZX Power",
  "city": null,
  "country": null,
  "issue_label": "01",
  "issue_date_iso": "1996-10-11",
  "order": 14,
  "article_id": 2647,
  "title_link": "Отдохнем - Советы первокурсснику или варианты конспектирования скучных\r\n лекций : конспект одного крутого студента ; глосарий.",
  "title_h1": "ZX Power 01 - Отдохнем - Советы первокурсснику или варианты конспектирования скучных  лекций : конспект одного крутого студента ; глосарий.",
  "print_url": "https://zxpress.ru/print.php?id=2647",
  "article_url": "https://zxpress.ru/article.php?id=2647",
  "fetched_at": "2026-05-31T23:35:05Z"
}