{
  "magazine_id": 224,
  "magazine_name": "Totoro",
  "city": null,
  "country": null,
  "issue_label": "01",
  "issue_date_iso": "2002-06-30",
  "order": 4,
  "article_id": 17678,
  "title_link": "Ламержди - Гoспoди, пoмилуй и упаси... oт зубoв неoпытных миньетчиц.",
  "title_h1": "Totoro 01 - Ламержди - Гoспoди, пoмилуй и упаси... oт зубoв неoпытных миньетчиц.",
  "print_url": "https://zxpress.ru/print.php?id=17678",
  "article_url": "https://zxpress.ru/article.php?id=17678",
  "fetched_at": "2026-05-31T23:14:38Z"
}