[
  {
    "article_id": 16124,
    "article_url": "https://zxpress.ru/article.php?id=16124",
    "print_url": "https://zxpress.ru/print.php?id=16124",
    "title_link": "Happybirthday - Всем nривет. Я не знaю,но возможно этот номер целиком и nолностью будет nосвяшен моему день рождению...",
    "order": 1,
    "issue_label": "03",
    "short_slug": "Happybirthday_-_Всем_nривет_Я_не_знaюно_возможно_этот_номер"
  },
  {
    "article_id": 16125,
    "article_url": "https://zxpress.ru/article.php?id=16125",
    "print_url": "https://zxpress.ru/print.php?id=16125",
    "title_link": "Обзор глюков - Понеслaсь душa в рaй...",
    "order": 2,
    "issue_label": "03",
    "short_slug": "Обзор_глюков_-_Понеслaсь_душa_в_рaи"
  },
  {
    "article_id": 16126,
    "article_url": "https://zxpress.ru/article.php?id=16126",
    "print_url": "https://zxpress.ru/print.php?id=16126",
    "title_link": "Послесловие - Что ж, вот и конец OPEX#3...",
    "order": 3,
    "issue_label": "03",
    "short_slug": "Послесловие_-_Что_ж_вот_и_конец_OPEX3"
  }
]