{
  "magazine_id": 42,
  "magazine_name": "City",
  "city": null,
  "country": null,
  "issue_label": "30",
  "issue_date_iso": "1999-09-25",
  "order": 6,
  "article_id": 10485,
  "title_link": "Beatles - Сегодня у нас стаpая, но очень хоpошая песня СОH-ТPАВА.",
  "title_h1": "City 30 - Beatles - Сегодня у нас стаpая, но очень хоpошая песня СОH-ТPАВА.",
  "print_url": "https://zxpress.ru/print.php?id=10485",
  "article_url": "https://zxpress.ru/article.php?id=10485",
  "fetched_at": "2026-05-31T21:51:14Z"
}