[
  {
    "article_id": 5108,
    "article_url": "https://zxpress.ru/article.php?id=5108",
    "print_url": "https://zxpress.ru/print.php?id=5108",
    "title_link": "Вступление - Беларусские новости из мира Спектрума.",
    "order": 1,
    "issue_label": "05",
    "short_slug": "Вступление_-_Беларусские_новости_из_мира_Спектрума"
  },
  {
    "article_id": 5109,
    "article_url": "https://zxpress.ru/article.php?id=5109",
    "print_url": "https://zxpress.ru/print.php?id=5109",
    "title_link": "Обзор warez'а - Обзор новинок ПО: Зеркало, Nenther Earth+, The Mission,\r\n Fisherman, Puzzle, The Last Courier, Операция Р.Р.,\r\n Волшебник Страны ОЗ, Sexmine Sniper, Fox Hunter,\r\n Lady in Love, Aany Tank, CLV-Copier v1.0, STS v6.2 ,\r\n Digital Studio Record, ZASM v3.10, Sample Studio.",
    "order": 2,
    "issue_label": "05",
    "short_slug": "Обзор_warezа_-_Обзор_новинок_ПО_Зеркало_Nenther_Earth_The_Mi"
  },
  {
    "article_id": 5110,
    "article_url": "https://zxpress.ru/article.php?id=5110",
    "print_url": "https://zxpress.ru/print.php?id=5110",
    "title_link": "Обзор warez'а - Обзор ПО выпущенного в Бресте в 96-97г: Compress Copy, New Copy, Real Copy, Echo 1-3, Tehcnodrom, Sprites Generator, Text Print, Text Format, Impulse 1, Code Disassembler, Cyber Dream, Password Protect Files, Installator Stealth Boot, Real Commander, Heavy on the Magic.",
    "order": 3,
    "issue_label": "05",
    "short_slug": "Обзор_warezа_-_Обзор_ПО_выпущенного_в_Бресте_в_96-97г_Compre"
  },
  {
    "article_id": 5111,
    "article_url": "https://zxpress.ru/article.php?id=5111",
    "print_url": "https://zxpress.ru/print.php?id=5111",
    "title_link": "Разборочка - Описание игры ОПЕРАЦИЯ Р.Р.",
    "order": 4,
    "issue_label": "05",
    "short_slug": "Разборочка_-_Описание_игры_ОПЕРАЦИЯ_РР"
  },
  {
    "article_id": 5112,
    "article_url": "https://zxpress.ru/article.php?id=5112",
    "print_url": "https://zxpress.ru/print.php?id=5112",
    "title_link": "Разборочка - Формат отгрузки в игре Bard'S Tale.",
    "order": 5,
    "issue_label": "05",
    "short_slug": "Разборочка_-_Формат_отгрузки_в_игре_BardS_Tale"
  },
  {
    "article_id": 5113,
    "article_url": "https://zxpress.ru/article.php?id=5113",
    "print_url": "https://zxpress.ru/print.php?id=5113",
    "title_link": "Разборочка - Несколько советов по прохождению игры Зеркало (MIRROR).",
    "order": 6,
    "issue_label": "05",
    "short_slug": "Разборочка_-_Несколько_советов_по_прохождению_игры_Зеркало_M"
  },
  {
    "article_id": 5114,
    "article_url": "https://zxpress.ru/article.php?id=5114",
    "print_url": "https://zxpress.ru/print.php?id=5114",
    "title_link": "Интервью - Интервью с автором серии демок \"Monsters\" - Inkognito Soft.",
    "order": 7,
    "issue_label": "05",
    "short_slug": "Интервью_-_Интервью_с_автором_серии_демок_Monsters_-_Inkogni"
  },
  {
    "article_id": 5115,
    "article_url": "https://zxpress.ru/article.php?id=5115",
    "print_url": "https://zxpress.ru/print.php?id=5115",
    "title_link": "Game Project - War in Space - новая стратегическая игра.",
    "order": 8,
    "issue_label": "05",
    "short_slug": "Game_Project_-_War_in_Space_-_новая_стратегическая_игра"
  },
  {
    "article_id": 5116,
    "article_url": "https://zxpress.ru/article.php?id=5116",
    "print_url": "https://zxpress.ru/print.php?id=5116",
    "title_link": "Программирование - Драйвер памяти.",
    "order": 9,
    "issue_label": "05",
    "short_slug": "Программирование_-_Драивер_памяти"
  },
  {
    "article_id": 5117,
    "article_url": "https://zxpress.ru/article.php?id=5117",
    "print_url": "https://zxpress.ru/print.php?id=5117",
    "title_link": "Программирование - Двойное разрешение на ZX-Spectrum.",
    "order": 10,
    "issue_label": "05",
    "short_slug": "Программирование_-_Двоиное_разрешение_на_ZX-Spectrum"
  },
  {
    "article_id": 5118,
    "article_url": "https://zxpress.ru/article.php?id=5118",
    "print_url": "https://zxpress.ru/print.php?id=5118",
    "title_link": "Советы хаккеру - Методика адаптирования авторских программ под систему\r\n TR-DOS (Методика взлома ZX-Format 8, Mortal Kombat).",
    "order": 11,
    "issue_label": "05",
    "short_slug": "Советы_хаккеру_-_Методика_адаптирования_авторских_программ_п"
  },
  {
    "article_id": 5119,
    "article_url": "https://zxpress.ru/article.php?id=5119",
    "print_url": "https://zxpress.ru/print.php?id=5119",
    "title_link": "Текстовые редакторы - Проблемы текстового ПО на Speccy.",
    "order": 12,
    "issue_label": "05",
    "short_slug": "Текстовые_редакторы_-_Проблемы_текстового_ПО_на_Speccy"
  },
  {
    "article_id": 5120,
    "article_url": "https://zxpress.ru/article.php?id=5120",
    "print_url": "https://zxpress.ru/print.php?id=5120",
    "title_link": "Железо - 122 цвета на спектруме: FLASH генератор цветов для ПК \"Байт\".",
    "order": 13,
    "issue_label": "05",
    "short_slug": "Железо_-_122_цвета_на_спектруме_FLASH_генератор_цветов_для_П"
  },
  {
    "article_id": 5121,
    "article_url": "https://zxpress.ru/article.php?id=5121",
    "print_url": "https://zxpress.ru/print.php?id=5121",
    "title_link": "Железо - Программируемый параллельный интерфейс КР580ВВ55А.",
    "order": 14,
    "issue_label": "05",
    "short_slug": "Железо_-_Программируемыи_параллельныи_интерфеис_КР580ВВ55А"
  },
  {
    "article_id": 5122,
    "article_url": "https://zxpress.ru/article.php?id=5122",
    "print_url": "https://zxpress.ru/print.php?id=5122",
    "title_link": "Technodrom-2 - История создания игры Technodrom'а.",
    "order": 15,
    "issue_label": "05",
    "short_slug": "Technodrom-2_-_История_создания_игры_Technodromа"
  },
  {
    "article_id": 5123,
    "article_url": "https://zxpress.ru/article.php?id=5123",
    "print_url": "https://zxpress.ru/print.php?id=5123",
    "title_link": "Сетевая игра - Пошаговая Сетевая игра со спектрумовскими персонажами.",
    "order": 16,
    "issue_label": "05",
    "short_slug": "Сетевая_игра_-_Пошаговая_Сетевая_игра_со_спектрумовскими_пер"
  },
  {
    "article_id": 5124,
    "article_url": "https://zxpress.ru/article.php?id=5124",
    "print_url": "https://zxpress.ru/print.php?id=5124",
    "title_link": "Письма - Спектрумисты на Могилевщине вымерли как мамонты.",
    "order": 17,
    "issue_label": "05",
    "short_slug": "Письма_-_Спектрумисты_на_Могилевщине_вымерли_как_мамонты"
  },
  {
    "article_id": 5125,
    "article_url": "https://zxpress.ru/article.php?id=5125",
    "print_url": "https://zxpress.ru/print.php?id=5125",
    "title_link": "Реклама - Реклама и объявления ...",
    "order": 18,
    "issue_label": "05",
    "short_slug": "Реклама_-_Реклама_и_объявления"
  }
]