[
  {
    "article_id": 14336,
    "article_url": "https://zxpress.ru/article.php?id=14336",
    "print_url": "https://zxpress.ru/print.php?id=14336",
    "title_link": "Содержание - авторы номера.",
    "order": 1,
    "issue_label": "11",
    "short_slug": "Содержание_-_авторы_номера"
  },
  {
    "article_id": 14337,
    "article_url": "https://zxpress.ru/article.php?id=14337",
    "print_url": "https://zxpress.ru/print.php?id=14337",
    "title_link": "Новости - Выход DMA мультикарты задерживается по\r\nтехническим причинам.",
    "order": 2,
    "issue_label": "11",
    "short_slug": "Новости_-_Выход_DMA_мультикарты_задерживается_потехническим"
  },
  {
    "article_id": 14338,
    "article_url": "https://zxpress.ru/article.php?id=14338",
    "print_url": "https://zxpress.ru/print.php?id=14338",
    "title_link": "Новинки - Черный Ворон с новыми миссиями, The Cezar, Net Walk 1998, Работы с DI:HALT'99, RUsH #2 1999.",
    "order": 3,
    "issue_label": "11",
    "short_slug": "Новинки_-_Черныи_Ворон_с_новыми_миссиями_The_Cezar_Net_Walk"
  },
  {
    "article_id": 14339,
    "article_url": "https://zxpress.ru/article.php?id=14339",
    "print_url": "https://zxpress.ru/print.php?id=14339",
    "title_link": "Программирование - сравнением качественных характеристик различных ассемблеров.",
    "order": 4,
    "issue_label": "11",
    "short_slug": "Программирование_-_сравнением_качественных_характеристик_раз"
  },
  {
    "article_id": 14340,
    "article_url": "https://zxpress.ru/article.php?id=14340",
    "print_url": "https://zxpress.ru/print.php?id=14340",
    "title_link": "Железо - описание, схема и программирование звуковой карты с прямым доступом DMA Sound Card.",
    "order": 5,
    "issue_label": "11",
    "short_slug": "Железо_-_описание_схема_и_программирование_звуковои_карты_с"
  },
  {
    "article_id": 14341,
    "article_url": "https://zxpress.ru/article.php?id=14341",
    "print_url": "https://zxpress.ru/print.php?id=14341",
    "title_link": "Железо - Последовательный порт для Spectrum'a",
    "order": 6,
    "issue_label": "11",
    "short_slug": "Железо_-_Последовательныи_порт_для_Spectruma"
  },
  {
    "article_id": 14342,
    "article_url": "https://zxpress.ru/article.php?id=14342",
    "print_url": "https://zxpress.ru/print.php?id=14342",
    "title_link": "Железо - история подключение Hayes модема в Уфе.",
    "order": 7,
    "issue_label": "11",
    "short_slug": "Железо_-_история_подключение_Hayes_модема_в_Уфе"
  },
  {
    "article_id": 14343,
    "article_url": "https://zxpress.ru/article.php?id=14343",
    "print_url": "https://zxpress.ru/print.php?id=14343",
    "title_link": "Железо - Версии теневого сервис монитора для ZS Scorpion.",
    "order": 8,
    "issue_label": "11",
    "short_slug": "Железо_-_Версии_теневого_сервис_монитора_для_ZS_Scorpion"
  },
  {
    "article_id": 14344,
    "article_url": "https://zxpress.ru/article.php?id=14344",
    "print_url": "https://zxpress.ru/print.php?id=14344",
    "title_link": "Игры - описание игры FIGHTER PILOT (Пилот истребителя).",
    "order": 9,
    "issue_label": "11",
    "short_slug": "Игры_-_описание_игры_FIGHTER_PILOT_Пилот_истребителя"
  },
  {
    "article_id": 14345,
    "article_url": "https://zxpress.ru/article.php?id=14345",
    "print_url": "https://zxpress.ru/print.php?id=14345",
    "title_link": "Интервью - уфимским кодером с Vasil из группы ChemneSoft.",
    "order": 10,
    "issue_label": "11",
    "short_slug": "Интервью_-_уфимским_кодером_с_Vasil_из_группы_ChemneSoft"
  },
  {
    "article_id": 14346,
    "article_url": "https://zxpress.ru/article.php?id=14346",
    "print_url": "https://zxpress.ru/print.php?id=14346",
    "title_link": "Demoparty - Официальное приглашение\r\n версия 0.1 на Cafe'2000.",
    "order": 11,
    "issue_label": "11",
    "short_slug": "Demoparty_-_Официальное_приглашение_версия_01_на_Cafe2000"
  },
  {
    "article_id": 14347,
    "article_url": "https://zxpress.ru/article.php?id=14347",
    "print_url": "https://zxpress.ru/print.php?id=14347",
    "title_link": "Обьявление - и реклама.",
    "order": 12,
    "issue_label": "11",
    "short_slug": "Обьявление_-_и_реклама"
  }
]