{
  "magazine_id": 9,
  "magazine_name": "Adventurer",
  "city": null,
  "country": null,
  "issue_label": "08",
  "issue_date_iso": "1998-08-31",
  "order": 20,
  "article_id": 5480,
  "title_link": "Раскрутка - описание игры Elopement: back to the Earth.",
  "title_h1": "Adventurer 08 - Раскрутка - описание игры Elopement: back to the Earth.",
  "print_url": "https://zxpress.ru/print.php?id=5480",
  "article_url": "https://zxpress.ru/article.php?id=5480",
  "fetched_at": "2026-05-31T21:33:44Z"
}