{
  "magazine_id": 204,
  "magazine_name": "Spectrophoby",
  "city": null,
  "country": null,
  "issue_label": "05",
  "issue_date_iso": "1996-07-31",
  "order": 13,
  "article_id": 12126,
  "title_link": "Система - генератор и редактор спрайтов: SCG v4.2.",
  "title_h1": "Spectrophoby 05 - Система - генератор и редактор спрайтов: SCG v4.2.",
  "print_url": "https://zxpress.ru/print.php?id=12126",
  "article_url": "https://zxpress.ru/article.php?id=12126",
  "fetched_at": "2026-05-31T23:07:11Z"
}