{
  "magazine_id": 93,
  "magazine_name": "Gothiq",
  "city": null,
  "country": null,
  "issue_label": "01",
  "issue_date_iso": "2003-01-14",
  "order": 8,
  "article_id": 11076,
  "title_link": "Coding - Directory System: описание системы каталогов для TR-DOS.",
  "title_h1": "Gothiq 01 - Coding - Directory System: описание системы каталогов для TR-DOS.",
  "print_url": "https://zxpress.ru/print.php?id=11076",
  "article_url": "https://zxpress.ru/article.php?id=11076",
  "fetched_at": "2026-05-31T22:11:20Z"
}