{
  "magazine_id": 191,
  "magazine_name": "Sinclair Town",
  "city": null,
  "country": null,
  "issue_label": "01",
  "issue_date_iso": "1995-03-31",
  "order": 15,
  "article_id": 9531,
  "title_link": "Архив - О программах существующих для ПК \"ZX-SPECTRUM\":\r\n AMAUROTE, ATIC ATAC, ALIEN HIGHWAY, ACE 2088,\r\n RESCATE ATLANTIDA part 1 & 2.",
  "title_h1": "Sinclair Town 01 - Архив - О программах существующих для ПК \"ZX-SPECTRUM\":  AMAUROTE, ATIC ATAC, ALIEN HIGHWAY, ACE 2088,  RESCATE ATLANTIDA part 1 & 2.",
  "print_url": "https://zxpress.ru/print.php?id=9531",
  "article_url": "https://zxpress.ru/article.php?id=9531",
  "fetched_at": "2026-05-31T23:02:13Z"
}