{
  "magazine_id": 70,
  "magazine_name": "Fanat",
  "city": null,
  "country": null,
  "issue_label": "01",
  "issue_date_iso": "1999-08-05",
  "order": 6,
  "article_id": 15134,
  "title_link": "Пятерка самых лучших - В этой рубрике я решил поместить 5 самых клевых игрушек для Спектрума, РС, и для эмуляторов различных игровых приставок.",
  "title_h1": "Fanat 01 - Пятерка самых лучших - В этой рубрике я решил поместить 5 самых клевых игрушек для Спектрума, РС, и для эмуляторов различных игровых приставок.",
  "print_url": "https://zxpress.ru/print.php?id=15134",
  "article_url": "https://zxpress.ru/article.php?id=15134",
  "fetched_at": "2026-05-31T22:03:48Z"
}