{
  "magazine_id": 89,
  "magazine_name": "Generation Z",
  "city": null,
  "country": null,
  "issue_label": "5,5",
  "issue_date_iso": "2009-01-20",
  "order": 8,
  "article_id": 6018,
  "title_link": "final words to scene - \"excelente!, - сказали бы сейчас мои испанские\r\nдрузья, и я бы с ними согласился.\"",
  "title_h1": "Generation Z 5,5 - final words to scene - \"excelente!, - сказали бы сейчас мои испанские друзья, и я бы с ними согласился.\"",
  "print_url": "https://zxpress.ru/print.php?id=6018",
  "article_url": "https://zxpress.ru/article.php?id=6018",
  "fetched_at": "2026-05-31T22:10:14Z"
}