[
  {
    "article_id": 17027,
    "article_url": "https://zxpress.ru/article.php?id=17027",
    "print_url": "https://zxpress.ru/print.php?id=17027",
    "title_link": "Пьянству-бой - Нерегулярное сорокоградусное-развлекательное издание.",
    "order": 1,
    "issue_label": "03",
    "short_slug": "Пьянству-бои_-_Нерегулярное_сорокоградусное-развлекательное"
  },
  {
    "article_id": 17028,
    "article_url": "https://zxpress.ru/article.php?id=17028",
    "print_url": "https://zxpress.ru/print.php?id=17028",
    "title_link": "Заслуженным алкоголикам всех времен и народов посвещается - Как вы думаете в каком состоянии собирается эта газета?",
    "order": 2,
    "issue_label": "03",
    "short_slug": "Заслуженным_алкоголикам_всех_времен_и_народов_посвещается_-"
  },
  {
    "article_id": 17029,
    "article_url": "https://zxpress.ru/article.php?id=17029",
    "print_url": "https://zxpress.ru/print.php?id=17029",
    "title_link": "История - Доклад Wolf'а от 324-ой сессии Верховного Съезда беларусских синклеристов.",
    "order": 3,
    "issue_label": "03",
    "short_slug": "История_-_Доклад_Wolfа_от_324-ои_сессии_Верховного_Съезда_бе"
  },
  {
    "article_id": 17030,
    "article_url": "https://zxpress.ru/article.php?id=17030",
    "print_url": "https://zxpress.ru/print.php?id=17030",
    "title_link": "История - Пьянка с участием всех беларусских групп: SERGEY STURM/LGN",
    "order": 4,
    "issue_label": "03",
    "short_slug": "История_-_Пьянка_с_участием_всех_беларусских_групп_SERGEY_ST"
  },
  {
    "article_id": 17031,
    "article_url": "https://zxpress.ru/article.php?id=17031",
    "print_url": "https://zxpress.ru/print.php?id=17031",
    "title_link": "История - Пьянка с участием всех беларусских групп: Firean/LGN",
    "order": 5,
    "issue_label": "03",
    "short_slug": "История_-_Пьянка_с_участием_всех_беларусских_групп_FireanLGN"
  },
  {
    "article_id": 17032,
    "article_url": "https://zxpress.ru/article.php?id=17032",
    "print_url": "https://zxpress.ru/print.php?id=17032",
    "title_link": "История - Пьянка с участием всех беларусских групп: woLF/RAGE!",
    "order": 6,
    "issue_label": "03",
    "short_slug": "История_-_Пьянка_с_участием_всех_беларусских_групп_woLFRAGE"
  },
  {
    "article_id": 17033,
    "article_url": "https://zxpress.ru/article.php?id=17033",
    "print_url": "https://zxpress.ru/print.php?id=17033",
    "title_link": "История - Пьянка с участием всех беларусских групп: ICE/PHD",
    "order": 7,
    "issue_label": "03",
    "short_slug": "История_-_Пьянка_с_участием_всех_беларусских_групп_ICEPHD"
  }
]