{
  "magazine_id": 176,
  "magazine_name": "RST",
  "city": null,
  "country": null,
  "issue_label": "04",
  "issue_date_iso": "2002-08-17",
  "order": 4,
  "article_id": 14912,
  "title_link": "Страна советов - Восстановлeниe дисков с полностью yничтожeнным систeмным трeком.",
  "title_h1": "RST 04 - Страна советов - Восстановлeниe дисков с полностью yничтожeнным систeмным трeком.",
  "print_url": "https://zxpress.ru/print.php?id=14912",
  "article_url": "https://zxpress.ru/article.php?id=14912",
  "fetched_at": "2026-05-31T22:57:40Z"
}