{
  "magazine_id": 102,
  "magazine_name": "Insanity",
  "city": null,
  "country": null,
  "issue_label": "03",
  "issue_date_iso": "1999-12-18",
  "order": 8,
  "article_id": 11642,
  "title_link": "Soft - описания навороченного плеера PT3 музыки - SPLAYЕR by SiRiL/4D.",
  "title_h1": "Insanity 03 - Soft - описания навороченного плеера PT3 музыки - SPLAYЕR by SiRiL/4D.",
  "print_url": "https://zxpress.ru/print.php?id=11642",
  "article_url": "https://zxpress.ru/article.php?id=11642",
  "fetched_at": "2026-05-31T22:14:14Z"
}