{
  "magazine_id": 107,
  "magazine_name": "KrNews",
  "city": null,
  "country": null,
  "issue_label": "06",
  "issue_date_iso": "1998-11-15",
  "order": 10,
  "article_id": 8266,
  "title_link": "INCOMING - Презентация игр: A LAST HERO of the LIGHT FORCE ORCS LAIR & MONSTR LAND.",
  "title_h1": "KrNews 06 - INCOMING - Презентация игр: A LAST HERO of the LIGHT FORCE ORCS LAIR & MONSTR LAND.",
  "print_url": "https://zxpress.ru/print.php?id=8266",
  "article_url": "https://zxpress.ru/article.php?id=8266",
  "fetched_at": "2026-05-31T22:17:20Z"
}