{
  "magazine_id": 145,
  "magazine_name": "Odyssey paper",
  "city": null,
  "country": null,
  "issue_label": "06",
  "issue_date_iso": "1999-02-25",
  "order": 2,
  "article_id": 9627,
  "title_link": "Новости - я сделал boot, Fatality сделали игру Kolobok 2.",
  "title_h1": "Odyssey paper 06 - Новости - я сделал boot, Fatality сделали игру Kolobok 2.",
  "print_url": "https://zxpress.ru/print.php?id=9627",
  "article_url": "https://zxpress.ru/article.php?id=9627",
  "fetched_at": "2026-05-31T22:41:11Z"
}