{
  "magazine_id": 147,
  "magazine_name": "On-Line",
  "city": null,
  "country": null,
  "issue_label": "10",
  "issue_date_iso": "1995-11-12",
  "order": 3,
  "article_id": 1962,
  "title_link": "Scorpion Club - Открыта новая B.B.S. О разработке новой TR-DOS совместимой оболочки.",
  "title_h1": "On-Line 10 - Scorpion Club - Открыта новая B.B.S. О разработке новой TR-DOS совместимой оболочки.",
  "print_url": "https://zxpress.ru/print.php?id=1962",
  "article_url": "https://zxpress.ru/article.php?id=1962",
  "fetched_at": "2026-05-31T22:42:00Z"
}