{
  "magazine_id": 67,
  "magazine_name": "Energy",
  "city": null,
  "country": null,
  "issue_label": "01",
  "issue_date_iso": "1998-03-31",
  "order": 6,
  "article_id": 3851,
  "title_link": "Письма - Отзывы FiloSof'а на темы затронутые газетами, мессагами и\r\n устными разговорами.",
  "title_h1": "Energy 01 - Письма - Отзывы FiloSof'а на темы затронутые газетами, мессагами и  устными разговорами.",
  "print_url": "https://zxpress.ru/print.php?id=3851",
  "article_url": "https://zxpress.ru/article.php?id=3851",
  "fetched_at": "2026-05-31T22:02:05Z"
}