{
  "magazine_id": 42,
  "magazine_name": "City",
  "city": null,
  "country": null,
  "issue_label": "27",
  "issue_date_iso": "1999-09-09",
  "order": 7,
  "article_id": 10466,
  "title_link": "Beatles - одна из многочисленных песен нашей же легендаpной МАШИHЫ ВPЕМЕHИ.",
  "title_h1": "City 27 - Beatles - одна из многочисленных песен нашей же легендаpной МАШИHЫ ВPЕМЕHИ.",
  "print_url": "https://zxpress.ru/print.php?id=10466",
  "article_url": "https://zxpress.ru/article.php?id=10466",
  "fetched_at": "2026-05-31T21:51:07Z"
}