{
  "magazine_id": 100,
  "magazine_name": "Inferno",
  "city": null,
  "country": null,
  "issue_label": "04",
  "issue_date_iso": "2003-06-22",
  "order": 20,
  "article_id": 8741,
  "title_link": "Others - Зарегистрированные пользователи ZXVGS и CPM22QED.",
  "title_h1": "Inferno 04 - Others - Зарегистрированные пользователи ZXVGS и CPM22QED.",
  "print_url": "https://zxpress.ru/print.php?id=8741",
  "article_url": "https://zxpress.ru/article.php?id=8741",
  "fetched_at": "2026-05-31T22:13:46Z"
}