{
  "magazine_id": 107,
  "magazine_name": "KrNews",
  "city": null,
  "country": null,
  "issue_label": "00",
  "issue_date_iso": "1998-01-09",
  "order": 6,
  "article_id": 1801,
  "title_link": "Новости - Новинки ПО: Зеркало-demo, 12 Тайных Книг-demo, Fizzy, Kalah,\r\n Judge Dredd, Run for Glog, Pro Sound Creator v1.3, DASM v1.0. Новости из разных городов.",
  "title_h1": "KrNews 00 - Новости - Новинки ПО: Зеркало-demo, 12 Тайных Книг-demo, Fizzy, Kalah,  Judge Dredd, Run for Glog, Pro Sound Creator v1.3, DASM v1.0. Новости из разных городов.",
  "print_url": "https://zxpress.ru/print.php?id=1801",
  "article_url": "https://zxpress.ru/article.php?id=1801",
  "fetched_at": "2026-05-31T22:16:45Z"
}