{
  "magazine_id": 9,
  "magazine_name": "Adventurer",
  "city": null,
  "country": null,
  "issue_label": "13",
  "issue_date_iso": "2002-03-31",
  "order": 39,
  "article_id": 10050,
  "title_link": "Chaos Construction 2001 - интервью с Pheel и EA из Antares.",
  "title_h1": "Adventurer 13 - Chaos Construction 2001 - интервью с Pheel и EA из Antares.",
  "print_url": "https://zxpress.ru/print.php?id=10050",
  "article_url": "https://zxpress.ru/article.php?id=10050",
  "fetched_at": "2026-05-31T21:35:12Z"
}