{
  "magazine_id": 202,
  "magazine_name": "Spectrofon",
  "city": null,
  "country": null,
  "issue_label": "09",
  "issue_date_iso": "1994-09-30",
  "order": 4,
  "article_id": 4689,
  "title_link": "Экзамен - рецепты идельных ограблений в игре \"They Stole a million\".",
  "title_h1": "Spectrofon 09 - Экзамен - рецепты идельных ограблений в игре \"They Stole a million\".",
  "print_url": "https://zxpress.ru/print.php?id=4689",
  "article_url": "https://zxpress.ru/article.php?id=4689",
  "fetched_at": "2026-05-31T23:05:30Z"
}