{
  "magazine_id": 28,
  "magazine_name": "Body",
  "city": null,
  "country": null,
  "issue_label": "28",
  "issue_date_iso": "2001-03-25",
  "order": 2,
  "article_id": 13143,
  "title_link": "wArЫz! - BlackCrown #5, SlangPro_demo, SpaceCrusade, Rainbow_demo.",
  "title_h1": "Body 28 - wArЫz! - BlackCrown #5, SlangPro_demo, SpaceCrusade, Rainbow_demo.",
  "print_url": "https://zxpress.ru/print.php?id=13143",
  "article_url": "https://zxpress.ru/article.php?id=13143",
  "fetched_at": "2026-05-31T21:42:29Z"
}