{
  "magazine_id": 50,
  "magazine_name": "Deja Vu",
  "city": null,
  "country": null,
  "issue_label": "09",
  "issue_date_iso": "1999-11-13",
  "order": 5,
  "article_id": 4778,
  "title_link": "Тема - Swap: \"От письма до бандероли\" как найти в своем городе Спектрумистов.",
  "title_h1": "Deja Vu 09 - Тема - Swap: \"От письма до бандероли\" как найти в своем городе Спектрумистов.",
  "print_url": "https://zxpress.ru/print.php?id=4778",
  "article_url": "https://zxpress.ru/article.php?id=4778",
  "fetched_at": "2026-05-31T21:55:43Z"
}