{
  "magazine_id": 95,
  "magazine_name": "Heresy",
  "city": null,
  "country": null,
  "issue_label": "10",
  "issue_date_iso": "0000-01-01",
  "order": 4,
  "article_id": 16488,
  "title_link": "Milchar: 效褌o ec褌褜 小a褌a薪懈蟹m? - 袙 m懈褉e 写e泄c褌胁y褞褌 褉a蟹谢懈褔薪褘e c懈谢褘, 泻a卸写a褟 懈蟹 泻o褌o褉褘褏 o泻a蟹褘胁ae褌 c胁oe 胁谢懈褟薪懈e 薪a 胁ce, 褔褌o 锌褉o懈c褏o写懈褌 胁o泻褉y谐 薪ac...",
  "title_h1": "Heresy 10 - Milchar: 效褌o ec褌褜 小a褌a薪懈蟹m? - 袙 m懈褉e 写e泄c褌胁y褞褌 褉a蟹谢懈褔薪褘e c懈谢褘, 泻a卸写a褟 懈蟹 泻o褌o褉褘褏 o泻a蟹褘胁ae褌 c胁oe 胁谢懈褟薪懈e 薪a 胁ce, 褔褌o 锌褉o懈c褏o写懈褌 胁o泻褉y谐 薪ac...",
  "print_url": "https://zxpress.ru/print.php?id=16488",
  "article_url": "https://zxpress.ru/article.php?id=16488",
  "fetched_at": "2026-05-31T22:12:30Z"
}