[
  {
    "article_id": 11721,
    "article_url": "https://zxpress.ru/article.php?id=11721",
    "print_url": "https://zxpress.ru/print.php?id=11721",
    "title_link": "Fantasy - наше Хобби - книги в жанре Фэнтези.",
    "order": 1,
    "issue_label": "01",
    "short_slug": "Fantasy_-_наше_Хобби_-_книги_в_жанре_Фэнтези"
  },
  {
    "article_id": 11722,
    "article_url": "https://zxpress.ru/article.php?id=11722",
    "print_url": "https://zxpress.ru/print.php?id=11722",
    "title_link": "Инфо - глюки в программах: Color Lines, ZX ZIP, Boot program, Mercenary: Escape from Targ, Honey Commander v4.0.",
    "order": 2,
    "issue_label": "01",
    "short_slug": "Инфо_-_глюки_в_программах_Color_Lines_ZX_ZIP_Boot_program_Me"
  },
  {
    "article_id": 11730,
    "article_url": "https://zxpress.ru/article.php?id=11730",
    "print_url": "https://zxpress.ru/print.php?id=11730",
    "title_link": "Инфо - The hackers: хакеры в Лас-Вегасе устраивают свой сьезд.",
    "order": 3,
    "issue_label": "01",
    "short_slug": "Инфо_-_The_hackers_хакеры_в_Лас-Вегасе_устраивают_свои_сьезд"
  },
  {
    "article_id": 11731,
    "article_url": "https://zxpress.ru/article.php?id=11731",
    "print_url": "https://zxpress.ru/print.php?id=11731",
    "title_link": "Инфо - Вскоре я, без особого на то желания и удовольствия, пересяду\r\nна платформу PC.",
    "order": 4,
    "issue_label": "01",
    "short_slug": "Инфо_-_Вскоре_я_без_особого_на_то_желания_и_удовольствия_пер"
  },
  {
    "article_id": 11723,
    "article_url": "https://zxpress.ru/article.php?id=11723",
    "print_url": "https://zxpress.ru/print.php?id=11723",
    "title_link": "Железо - маленькая заметка об улучшении\r\nмодемной связи - простейший\r\nRC-фильтр.",
    "order": 5,
    "issue_label": "01",
    "short_slug": "Железо_-_маленькая_заметка_об_улучшениимодемнои_связи_-_прос"
  },
  {
    "article_id": 11724,
    "article_url": "https://zxpress.ru/article.php?id=11724",
    "print_url": "https://zxpress.ru/print.php?id=11724",
    "title_link": "Система - о командах \"Принудительное прерывание\" мелкосхемы\r\nконтроллера флоппи-дисков КР1818ВГ93.",
    "order": 6,
    "issue_label": "01",
    "short_slug": "Система_-_о_командах_Принудительное_прерывание_мелкосхемыкон"
  },
  {
    "article_id": 11725,
    "article_url": "https://zxpress.ru/article.php?id=11725",
    "print_url": "https://zxpress.ru/print.php?id=11725",
    "title_link": "Глюк - Глюк он и в Африке глюк.",
    "order": 7,
    "issue_label": "01",
    "short_slug": "Глюк_-_Глюк_он_и_в_Африке_глюк"
  },
  {
    "article_id": 11726,
    "article_url": "https://zxpress.ru/article.php?id=11726",
    "print_url": "https://zxpress.ru/print.php?id=11726",
    "title_link": "Обзор - Клятва Ночи, STS, Code Cruncher, Battle Command.",
    "order": 8,
    "issue_label": "01",
    "short_slug": "Обзор_-_Клятва_Ночи_STS_Code_Cruncher_Battle_Command"
  },
  {
    "article_id": 11727,
    "article_url": "https://zxpress.ru/article.php?id=11727",
    "print_url": "https://zxpress.ru/print.php?id=11727",
    "title_link": "Отдых - в отдыхалке приколы из FIDONET и приколы, случившиеся со мной.",
    "order": 9,
    "issue_label": "01",
    "short_slug": "Отдых_-_в_отдыхалке_приколы_из_FIDONET_и_приколы_случившиеся"
  },
  {
    "article_id": 11728,
    "article_url": "https://zxpress.ru/article.php?id=11728",
    "print_url": "https://zxpress.ru/print.php?id=11728",
    "title_link": "Cheats - cheat'ы к некоторым игрушкам.",
    "order": 10,
    "issue_label": "01",
    "short_slug": "Cheats_-_cheatы_к_некоторым_игрушкам"
  },
  {
    "article_id": 11729,
    "article_url": "https://zxpress.ru/article.php?id=11729",
    "print_url": "https://zxpress.ru/print.php?id=11729",
    "title_link": "Другой мир - Шахматная система Deep Blue.",
    "order": 11,
    "issue_label": "01",
    "short_slug": "Другои_мир_-_Шахматная_система_Deep_Blue"
  },
  {
    "article_id": 14353,
    "article_url": "https://zxpress.ru/article.php?id=14353",
    "print_url": "https://zxpress.ru/print.php?id=14353",
    "title_link": "Железо - VICOMM - совместимый модем от MSD group.",
    "order": 12,
    "issue_label": "01",
    "short_slug": "Железо_-_VICOMM_-_совместимыи_модем_от_MSD_group"
  },
  {
    "article_id": 17881,
    "article_url": "https://zxpress.ru/article.php?id=17881",
    "print_url": "https://zxpress.ru/print.php?id=17881",
    "title_link": "Chinese Proverbs",
    "order": 13,
    "issue_label": "01",
    "short_slug": "Chinese_Proverbs"
  },
  {
    "article_id": 334,
    "article_url": "https://zxpress.ru/article.php?id=334",
    "print_url": "https://zxpress.ru/print.php?id=334",
    "title_link": "Почтовый ящик - Обмен опытом: читы",
    "order": 14,
    "issue_label": "01",
    "short_slug": "Почтовыи_ящик_-_Обмен_опытом_читы"
  },
  {
    "article_id": 2899,
    "article_url": "https://zxpress.ru/article.php?id=2899",
    "print_url": "https://zxpress.ru/print.php?id=2899",
    "title_link": "Список BBS - Список BBS. Открылась новая I.P.S. BBS.",
    "order": 15,
    "issue_label": "01",
    "short_slug": "Список_BBS_-_Список_BBS_Открылась_новая_IPS_BBS"
  },
  {
    "article_id": 3850,
    "article_url": "https://zxpress.ru/article.php?id=3850",
    "print_url": "https://zxpress.ru/print.php?id=3850",
    "title_link": "Приложение - Предложение...",
    "order": 16,
    "issue_label": "01",
    "short_slug": "Приложение_-_Предложение"
  }
]