{
  "magazine_id": 196,
  "magazine_name": "SOSG",
  "city": null,
  "country": null,
  "issue_label": "03",
  "issue_date_iso": "1999-11-12",
  "order": 2,
  "article_id": 13725,
  "title_link": "Всё о спектрумовских играх - о том, как НЕ НАДО писать адвентюрные программы \"Island of darkness\".",
  "title_h1": "SOSG 03 - Всё о спектрумовских играх - о том, как НЕ НАДО писать адвентюрные программы \"Island of darkness\".",
  "print_url": "https://zxpress.ru/print.php?id=13725",
  "article_url": "https://zxpress.ru/article.php?id=13725",
  "fetched_at": "2026-05-31T23:03:31Z"
}