{
  "magazine_id": 136,
  "magazine_name": "Netus News",
  "city": null,
  "country": null,
  "issue_label": "09",
  "issue_date_iso": "1999-01-19",
  "order": 9,
  "article_id": 10998,
  "title_link": "Лечение смехом - Вопросы и ответы советской экспеpтной системы или армянского радио.",
  "title_h1": "Netus News 09 - Лечение смехом - Вопросы и ответы советской экспеpтной системы или армянского радио.",
  "print_url": "https://zxpress.ru/print.php?id=10998",
  "article_url": "https://zxpress.ru/article.php?id=10998",
  "fetched_at": "2026-05-31T22:31:56Z"
}