{
  "magazine_id": 26,
  "magazine_name": "Black Crow",
  "city": null,
  "country": null,
  "issue_label": "03",
  "issue_date_iso": "2000-06-27",
  "order": 17,
  "article_id": 14738,
  "title_link": "Игротека - Прохождение игр: 12 Тайныx Книг, Twillight.",
  "title_h1": "Black Crow 03 - Игротека - Прохождение игр: 12 Тайныx Книг, Twillight.",
  "print_url": "https://zxpress.ru/print.php?id=14738",
  "article_url": "https://zxpress.ru/article.php?id=14738",
  "fetched_at": "2026-05-31T21:39:24Z"
}