[
  {
    "article_id": 7205,
    "article_url": "https://zxpress.ru/article.php?id=7205",
    "print_url": "https://zxpress.ru/print.php?id=7205",
    "title_link": "Вступление - содержание номера.",
    "order": 1,
    "issue_label": "109",
    "short_slug": "Вступление_-_содержание_номера"
  },
  {
    "article_id": 7206,
    "article_url": "https://zxpress.ru/article.php?id=7206",
    "print_url": "https://zxpress.ru/print.php?id=7206",
    "title_link": "Разное - Дожить до \"Русбата\". О конфликте в Косово.",
    "order": 2,
    "issue_label": "109",
    "short_slug": "Разное_-_Дожить_до_Русбата_О_конфликте_в_Косово"
  },
  {
    "article_id": 7207,
    "article_url": "https://zxpress.ru/article.php?id=7207",
    "print_url": "https://zxpress.ru/print.php?id=7207",
    "title_link": "Пресса - Вести со сцены. Статья из газеты \"Труд и жизнь\".",
    "order": 3,
    "issue_label": "109",
    "short_slug": "Пресса_-_Вести_со_сцены_Статья_из_газеты_Труд_и_жизнь"
  },
  {
    "article_id": 7208,
    "article_url": "https://zxpress.ru/article.php?id=7208",
    "print_url": "https://zxpress.ru/print.php?id=7208",
    "title_link": "События - сисопник. Фото.",
    "order": 4,
    "issue_label": "109",
    "short_slug": "События_-_сисопник_Фото"
  },
  {
    "article_id": 7209,
    "article_url": "https://zxpress.ru/article.php?id=7209",
    "print_url": "https://zxpress.ru/print.php?id=7209",
    "title_link": "Рассказы - Семь дней - семь ночей (продолжение).",
    "order": 5,
    "issue_label": "109",
    "short_slug": "Рассказы_-_Семь_днеи_-_семь_ночеи_продолжение"
  },
  {
    "article_id": 7210,
    "article_url": "https://zxpress.ru/article.php?id=7210",
    "print_url": "https://zxpress.ru/print.php?id=7210",
    "title_link": "Реклама - реклама и объявления.",
    "order": 6,
    "issue_label": "109",
    "short_slug": "Реклама_-_реклама_и_объявления"
  },
  {
    "article_id": 7211,
    "article_url": "https://zxpress.ru/article.php?id=7211",
    "print_url": "https://zxpress.ru/print.php?id=7211",
    "title_link": "Обратная связь - контакты редакции.",
    "order": 7,
    "issue_label": "109",
    "short_slug": "Обратная_связь_-_контакты_редакции"
  }
]