{
  "magazine_id": 95,
  "magazine_name": "Heresy",
  "city": null,
  "country": null,
  "issue_label": "08",
  "issue_date_iso": "0000-01-01",
  "order": 4,
  "article_id": 16458,
  "title_link": "FUCK P–źR–Ę - –°—Üe–Ĺo–≤—če –Īy–ī–Ĺ–ł: \"Keep the Scene 4ever!\" - –Ě—č–Ĺ—áe, –Ņ—Äo–≥—Äecc–ł–≤–Ĺy—é —áac—ā—Ć c–Ņe–ļ—ā—Äymo–≤c–ļo–≥o coo–Ī—Čec—ā–≤a mo–ī–Ĺo –łme–Ĺo–≤a—ā—Ć c—Üe–Ĺe—Äam–ł...",
  "title_h1": "Heresy 08 - FUCK P–źR–Ę - –°—Üe–Ĺo–≤—če –Īy–ī–Ĺ–ł: \"Keep the Scene 4ever!\" - –Ě—č–Ĺ—áe, –Ņ—Äo–≥—Äecc–ł–≤–Ĺy—é —áac—ā—Ć c–Ņe–ļ—ā—Äymo–≤c–ļo–≥o coo–Ī—Čec—ā–≤a mo–ī–Ĺo –łme–Ĺo–≤a—ā—Ć c—Üe–Ĺe—Äam–ł...",
  "print_url": "https://zxpress.ru/print.php?id=16458",
  "article_url": "https://zxpress.ru/article.php?id=16458",
  "fetched_at": "2026-05-31T22:12:18Z"
}